tfops_aug/__init__.py
tfops_aug/augmentation_operations.py
tfops_aug/augmentation_policies.py
tfops_aug/augmentation_utils.py
tfops_aug/tests/__init__.py
tfops_aug/tests/augmentation_operations_test.py
tfops_aug/tests/augmentation_policies_test.py
tfops_aug/tests/augmentation_utils_test.py
tfops_aug-0.0.2.dist-info/METADATA
tfops_aug-0.0.2.dist-info/WHEEL
tfops_aug-0.0.2.dist-info/licenses/LICENSE
tfops_aug-0.0.2.dist-info/RECORD
