Metadata-Version: 2.1
Name: tfops_aug
Version: 0.0.2
Summary: Package to augment images using Tensorflow Ops
Project-URL: Homepage, https://github.com/TillBeemelmanns/auto-augment-tf2-operations
Project-URL: Bug Tracker, https://github.com/TillBeemelmanns/auto-augment-tf2-operations/issues
Author-email: Till Beemelmanns <till.beemelmanns@rwth-aachen.de>
License-File: LICENSE
Classifier: License :: OSI Approved :: MIT License
Classifier: Operating System :: OS Independent
Classifier: Programming Language :: Python :: 3
Requires-Python: >=3.9
Requires-Dist: matplotlib
Requires-Dist: numpy
Requires-Dist: opencv-python
Requires-Dist: tensorflow-addons==0.19.0
